Metadata-Version: 1.1
Name: pyblinkm
Version: 0.1.0
Summary: Drive a BlinkM with Python via I2C using python-smbus on Raspberry Pi.
Home-page: https://github.com/tsileo/pyblinkm
Author: Thomas Sileo
Author-email: thomas.sileo@gmail.com
License: MIT
Keywords: blinkm led i2c smbus rpi raspberry
Platform: UNKNOWN
Classifier: Development Status :: 4 - Beta
Classifier: Intended Audience :: Developers
Classifier: Topic :: Communications
Classifier: License :: OSI Approved :: MIT License
Classifier: Programming Language :: Python
